{
  "categories": [
    {"id":"tax","name":"稅務申報","icon":"📋","color":"#27a882"},
    {"id":"estate","name":"房地產稅務","icon":"🏠","color":"#e67e22"},
    {"id":"inherit","name":"遺產與贈與稅","icon":"💰","color":"#2980b9"},
    {"id":"insurance","name":"保險法規","icon":"🛡","color":"#8e44ad"},
    {"id":"finance","name":"金融市場","icon":"🏦","color":"#16a085"},
    {"id":"law","name":"法律判例","icon":"⚖️","color":"#c0392b"},
    {"id":"invest","name":"投資理財","icon":"📈","color":"#2c3e50"},
    {"id":"family","name":"家庭財務","icon":"👨‍👩‍👧","color":"#d35400"},
    {"id":"trend","name":"產業趨勢","icon":"📰","color":"#7f8c8d"}
  ],
  "articles": [
    {
      "cat":"tax",
      "title":"報稅季將至！房租特別扣除額拉高至18萬元，申報年增二成",
      "date":"2025-04-15",
      "source":"Yahoo財經",
      "summary":"114年度報稅新制，租金支出特別扣除額從12萬提高至18萬元，預估申報戶數將增加兩成。",
      "url":"https://tw.stock.yahoo.com/news/%E5%A0%B1%E7%A8%85%E5%AD%A3%E5%B0%87%E8%87%B3%EF%BC%81%E6%88%BF%E7%A7%9F%E7%89%B9%E5%88%A5%E6%89%A3%E9%99%A4%E9%A1%8D%E6%8B%89%E9%AB%98%E5%88%B018%E8%90%AC%E5%85%83%E7%94%B3%E5%A0%B1%E5%B9%B4%E5%A2%9E%E4%BA%8C%E6%88%90-050116480.html",
      "tags":["報稅","房租扣除","114年度"]
    },
    {
      "cat":"tax",
      "title":"（待補充標題）",
      "date":"2025-04-15",
      "source":"風傳媒",
      "summary":"（請貼上文章內容，我來整理摘要）",
      "url":"https://www.storm.mg/lifestyle/11115236",
      "tags":["稅務"]
    },
    {
      "cat":"tax",
      "title":"（待補充標題）",
      "date":"2020-07-08",
      "source":"今周刊",
      "summary":"（請貼上文章內容，我來整理摘要）",
      "url":"https://www.businesstoday.com.tw/article/category/183021/post/202007080018/",
      "tags":["稅務"]
    },
    {
      "cat":"tax",
      "title":"（待補充標題）",
      "date":"2025-04-15",
      "source":"經濟日報",
      "summary":"（請貼上文章內容，我來整理摘要）",
      "url":"https://money.udn.com/money/story/12040/8813458",
      "tags":["稅務"]
    },
    {
      "cat":"tax",
      "title":"（待補充標題）",
      "date":"2025-06-08",
      "source":"今周刊",
      "summary":"（請貼上文章內容，我來整理摘要）",
      "url":"https://www.businesstoday.com.tw/article/category/183021/post/202506080007/",
      "tags":["稅務"]
    },
    {
      "cat":"insurance",
      "title":"投保月配息投資型保單，身故理賠真的不計入遺產總額嗎？",
      "date":"2024-05-15",
      "source":"經濟日報",
      "summary":"業務員宣稱投資型保單身故理賠不計入遺產總額，但實務上國稅局會依實質課稅原則審查，高齡投保、躉繳等情形仍可能被課遺產稅。",
      "url":"https://money.udn.com/money/amp/story/12040/7881732",
      "tags":["投資型保單","遺產稅","實質課稅"]
    },
    {
      "cat":"tax",
      "title":"（待補充標題）",
      "date":"2023-07-01",
      "source":"風傳媒",
      "summary":"（請貼上文章內容，我來整理摘要）",
      "url":"https://www.storm.mg/lifestyle/5075920",
      "tags":["稅務"]
    }
  ]
}
